<annotation><filename>561.jpg</filename><path>/home/palm/PycharmProjects/seven/data1/1/561.jpg</path><size><width>1080</width><height>1920</height></size><object><name>Mirinda orange 440ml</name><bndbox><xmin>343</xmin><ymin>705</ymin><xmax>681</xmax><ymax>1382</ymax></bndbox></object><object><name>obj</name><bndbox><xmin>169</xmin><ymin>1438</ymin><xmax>652</xmax><ymax>1917</ymax></bndbox></object><object><name>obj</name><bndbox><xmin>61</xmin><ymin>865</ymin><xmax>354</xmax><ymax>1461</ymax></bndbox></object></annotation>