<annotation>
	<folder>0</folder>
	<filename>1341.jpg</filename>
	<path>D:\Users\Administrator\Desktop\0\1341.jpg</path>
	<source>
		<database>Unknown</database>
	</source>
	<size>
		<width>1080</width>
		<height>1920</height>
		<depth>3</depth>
	</size>
	<segmented>0</segmented>
	<object>
		<name>Benice 90ml</name>
		<pose>Unspecified</pose>
		<truncated>0</truncated>
		<difficult>0</difficult>
		<bndbox>
			<xmin>138</xmin>
			<ymin>1080</ymin>
			<xmax>516</xmax>
			<ymax>1300</ymax>
		</bndbox>
	</object>
</annotation>
