<annotation><filename>140.jpg</filename><path>/home/palm/PycharmProjects/seven/data1/1/140.jpg</path><size><width>1080</width><height>1920</height></size><object><name>Nescafe_blend'nbrew_espresso_157.5g</name><bndbox><xmin>461</xmin><ymin>236</ymin><xmax>973</xmax><ymax>1208</ymax></bndbox></object><object><name>Birdy 3 in 1 robusta 62g</name><bndbox><xmin>93</xmin><ymin>455</ymin><xmax>462</xmax><ymax>1095</ymax></bndbox></object><object><name>Kellogg's corn flakes 25g</name><bndbox><xmin>149</xmin><ymin>1338</ymin><xmax>651</xmax><ymax>1914</ymax></bndbox></object><object><name>Jolly cola 25g</name><bndbox><xmin>35</xmin><ymin>1077</ymin><xmax>326</xmax><ymax>1531</ymax></bndbox></object><object><name>Jolly bear 25g</name><bndbox><xmin>8</xmin><ymin>702</ymin><xmax>153</xmax><ymax>1094</ymax></bndbox></object></annotation>