<annotation><filename>2211.jpg</filename><path>/home/palm/PycharmProjects/seven/data1/0/2211.jpg</path><size><width>1080</width><height>1920</height></size><object><name>obj</name><bndbox><xmin>0</xmin><ymin>316</ymin><xmax>922</xmax><ymax>1363</ymax></bndbox></object><object><name>obj</name><bndbox><xmin>314</xmin><ymin>470</ymin><xmax>961</xmax><ymax>1278</ymax></bndbox></object><object><name>obj</name><bndbox><xmin>0</xmin><ymin>199</ymin><xmax>610</xmax><ymax>1123</ymax></bndbox></object></annotation>