<annotation><filename>838.jpg</filename><path>/home/palm/PycharmProjects/seven/data1/0/838.jpg</path><size><width>1080</width><height>1920</height></size><object><name>obj</name><bndbox><xmin>497</xmin><ymin>0</ymin><xmax>1026</xmax><ymax>605</ymax></bndbox></object><object><name>obj</name><bndbox><xmin>256</xmin><ymin>1109</ymin><xmax>637</xmax><ymax>1726</ymax></bndbox></object><object><name>obj</name><bndbox><xmin>695</xmin><ymin>1075</ymin><xmax>1025</xmax><ymax>1580</ymax></bndbox></object><object><name>obj</name><bndbox><xmin>485</xmin><ymin>626</ymin><xmax>1043</xmax><ymax>964</ymax></bndbox></object><object><name>obj</name><bndbox><xmin>498</xmin><ymin>769</ymin><xmax>1046</xmax><ymax>1072</ymax></bndbox></object><object><name>obj</name><bndbox><xmin>0</xmin><ymin>630</ymin><xmax>186</xmax><ymax>1101</ymax></bndbox></object></annotation>