<annotation><filename>1193.jpg</filename><path>/home/palm/PycharmProjects/seven/data1/2/1193.jpg</path><size><width>1080</width><height>1920</height></size><object><name>obj</name><bndbox><xmin>542</xmin><ymin>837</ymin><xmax>1051</xmax><ymax>1772</ymax></bndbox></object><object><name>obj</name><bndbox><xmin>84</xmin><ymin>441</ymin><xmax>602</xmax><ymax>1012</ymax></bndbox></object><object><name>obj</name><bndbox><xmin>100</xmin><ymin>1079</ymin><xmax>574</xmax><ymax>1659</ymax></bndbox></object></annotation>