<annotation><filename>1487.jpg</filename><path>/home/palm/PycharmProjects/seven/data1/2/1487.jpg</path><size><width>1080</width><height>1920</height></size><object><name>obj</name><bndbox><xmin>306</xmin><ymin>1224</ymin><xmax>799</xmax><ymax>1920</ymax></bndbox></object><object><name>obj</name><bndbox><xmin>150</xmin><ymin>557</ymin><xmax>484</xmax><ymax>1126</ymax></bndbox></object><object><name>obj</name><bndbox><xmin>559</xmin><ymin>617</ymin><xmax>933</xmax><ymax>1193</ymax></bndbox></object></annotation>