<annotation><filename>1679.jpg</filename><path>/home/palm/PycharmProjects/seven/data1/2/1679.jpg</path><size><width>1080</width><height>1920</height></size><object><name>obj</name><bndbox><xmin>65</xmin><ymin>760</ymin><xmax>420</xmax><ymax>1148</ymax></bndbox></object><object><name>obj</name><bndbox><xmin>397</xmin><ymin>938</ymin><xmax>958</xmax><ymax>1637</ymax></bndbox></object><object><name>obj</name><bndbox><xmin>0</xmin><ymin>1491</ymin><xmax>396</xmax><ymax>1920</ymax></bndbox></object></annotation>