<annotation><filename>1702.jpg</filename><path>/home/palm/PycharmProjects/seven/data1/2/1702.jpg</path><size><width>1080</width><height>1920</height></size><object><name>obj</name><bndbox><xmin>454</xmin><ymin>732</ymin><xmax>626</xmax><ymax>987</ymax></bndbox></object><object><name>obj</name><bndbox><xmin>326</xmin><ymin>1045</ymin><xmax>496</xmax><ymax>1422</ymax></bndbox></object><object><name>obj</name><bndbox><xmin>533</xmin><ymin>1004</ymin><xmax>809</xmax><ymax>1402</ymax></bndbox></object></annotation>