<annotation><filename>1707.jpg</filename><path>/home/palm/PycharmProjects/seven/data1/2/1707.jpg</path><size><width>1080</width><height>1920</height></size><object><name>obj</name><bndbox><xmin>530</xmin><ymin>812</ymin><xmax>946</xmax><ymax>1244</ymax></bndbox></object><object><name>obj</name><bndbox><xmin>101</xmin><ymin>817</ymin><xmax>479</xmax><ymax>1232</ymax></bndbox></object><object><name>obj</name><bndbox><xmin>572</xmin><ymin>379</ymin><xmax>760</xmax><ymax>805</ymax></bndbox></object></annotation>