<annotation><filename>1751.jpg</filename><path>/home/palm/PycharmProjects/seven/data1/2/1751.jpg</path><size><width>1080</width><height>1920</height></size><object><name>obj</name><bndbox><xmin>158</xmin><ymin>372</ymin><xmax>543</xmax><ymax>800</ymax></bndbox></object><object><name>obj</name><bndbox><xmin>200</xmin><ymin>1046</ymin><xmax>796</xmax><ymax>1288</ymax></bndbox></object><object><name>obj</name><bndbox><xmin>50</xmin><ymin>1689</ymin><xmax>506</xmax><ymax>1920</ymax></bndbox></object></annotation>