<annotation><filename>192.jpg</filename><path>/home/palm/PycharmProjects/seven/data1/2/192.jpg</path><size><width>1080</width><height>1920</height></size><object><name>obj</name><bndbox><xmin>77</xmin><ymin>719</ymin><xmax>601</xmax><ymax>964</ymax></bndbox></object><object><name>obj</name><bndbox><xmin>72</xmin><ymin>1003</ymin><xmax>591</xmax><ymax>1228</ymax></bndbox></object><object><name>obj</name><bndbox><xmin>698</xmin><ymin>618</ymin><xmax>892</xmax><ymax>1136</ymax></bndbox></object></annotation>