<annotation><filename>1973.jpg</filename><path>/home/palm/PycharmProjects/seven/data1/2/1973.jpg</path><size><width>1080</width><height>1920</height></size><object><name>obj</name><bndbox><xmin>466</xmin><ymin>932</ymin><xmax>882</xmax><ymax>1438</ymax></bndbox></object><object><name>obj</name><bndbox><xmin>101</xmin><ymin>1552</ymin><xmax>592</xmax><ymax>1876</ymax></bndbox></object><object><name>obj</name><bndbox><xmin>235</xmin><ymin>903</ymin><xmax>462</xmax><ymax>1305</ymax></bndbox></object><object><name>obj</name><bndbox><xmin>445</xmin><ymin>1685</ymin><xmax>879</xmax><ymax>1920</ymax></bndbox></object><object><name>obj</name><bndbox><xmin>161</xmin><ymin>1608</ymin><xmax>784</xmax><ymax>1920</ymax></bndbox></object></annotation>