<annotation><filename>2211.jpg</filename><path>/home/palm/PycharmProjects/seven/data1/2/2211.jpg</path><size><width>1080</width><height>1920</height></size><object><name>obj</name><bndbox><xmin>184</xmin><ymin>702</ymin><xmax>519</xmax><ymax>904</ymax></bndbox></object><object><name>obj</name><bndbox><xmin>578</xmin><ymin>688</ymin><xmax>856</xmax><ymax>934</ymax></bndbox></object><object><name>obj</name><bndbox><xmin>27</xmin><ymin>925</ymin><xmax>698</xmax><ymax>1157</ymax></bndbox></object></annotation>