<annotation><filename>230.jpg</filename><path>/home/palm/PycharmProjects/seven/data1/2/230.jpg</path><size><width>1080</width><height>1920</height></size><object><name>obj</name><bndbox><xmin>124</xmin><ymin>301</ymin><xmax>703</xmax><ymax>861</ymax></bndbox></object><object><name>obj</name><bndbox><xmin>672</xmin><ymin>204</ymin><xmax>1059</xmax><ymax>1208</ymax></bndbox></object><object><name>obj</name><bndbox><xmin>309</xmin><ymin>923</ymin><xmax>680</xmax><ymax>1264</ymax></bndbox></object></annotation>