<annotation><filename>28.jpg</filename><path>/home/palm/PycharmProjects/seven/data1/2/28.jpg</path><size><width>1080</width><height>1920</height></size><object><name>obj</name><bndbox><xmin>380</xmin><ymin>756</ymin><xmax>652</xmax><ymax>1030</ymax></bndbox></object><object><name>obj</name><bndbox><xmin>659</xmin><ymin>1099</ymin><xmax>930</xmax><ymax>1443</ymax></bndbox></object><object><name>obj</name><bndbox><xmin>203</xmin><ymin>1144</ymin><xmax>574</xmax><ymax>1300</ymax></bndbox></object></annotation>