<annotation><filename>31.jpg</filename><path>/home/palm/PycharmProjects/seven/data1/2/31.jpg</path><size><width>1080</width><height>1920</height></size><object><name>obj</name><bndbox><xmin>130</xmin><ymin>1149</ymin><xmax>726</xmax><ymax>1591</ymax></bndbox></object><object><name>obj</name><bndbox><xmin>248</xmin><ymin>881</ymin><xmax>687</xmax><ymax>1175</ymax></bndbox></object><object><name>obj</name><bndbox><xmin>765</xmin><ymin>955</ymin><xmax>987</xmax><ymax>1345</ymax></bndbox></object></annotation>