<annotation><filename>54.jpg</filename><path>/home/palm/PycharmProjects/seven/data1/2/54.jpg</path><size><width>1080</width><height>1920</height></size><object><name>obj</name><bndbox><xmin>70</xmin><ymin>1277</ymin><xmax>873</xmax><ymax>1627</ymax></bndbox></object><object><name>obj</name><bndbox><xmin>0</xmin><ymin>794</ymin><xmax>636</xmax><ymax>1055</ymax></bndbox></object><object><name>obj</name><bndbox><xmin>954</xmin><ymin>833</ymin><xmax>1080</xmax><ymax>1269</ymax></bndbox></object></annotation>