<annotation><filename>844.jpg</filename><path>/home/palm/PycharmProjects/seven/data1/0/844.jpg</path><size><width>1080</width><height>1920</height></size><object><name>obj</name><bndbox><xmin>184</xmin><ymin>0</ymin><xmax>933</xmax><ymax>730</ymax></bndbox></object><object><name>obj</name><bndbox><xmin>588</xmin><ymin>674</ymin><xmax>1080</xmax><ymax>1233</ymax></bndbox></object><object><name>obj</name><bndbox><xmin>186</xmin><ymin>762</ymin><xmax>485</xmax><ymax>998</ymax></bndbox></object><object><name>obj</name><bndbox><xmin>404</xmin><ymin>1042</ymin><xmax>649</xmax><ymax>1652</ymax></bndbox></object></annotation>