<annotation>
	<folder>0</folder>
	<filename>1895.jpg</filename>
	<path>E:\PIM\DeepLearning\data1\0\1895.jpg</path>
	<source>
		<database>Unknown</database>
	</source>
	<size>
		<width>1080</width>
		<height>1920</height>
		<depth>3</depth>
	</size>
	<segmented>0</segmented>
	<object>
		<name>Parrot herbel organic pink 70g</name>
		<pose>Unspecified</pose>
		<truncated>1</truncated>
		<difficult>0</difficult>
		<bndbox>
			<xmin>779</xmin>
			<ymin>1354</ymin>
			<xmax>1080</xmax>
			<ymax>1695</ymax>
		</bndbox>
	</object>
	<object>
		<name>Baby mild sweety pink 50g</name>
		<pose>Unspecified</pose>
		<truncated>0</truncated>
		<difficult>0</difficult>
		<bndbox>
			<xmin>461</xmin>
			<ymin>660</ymin>
			<xmax>764</xmax>
			<ymax>918</ymax>
		</bndbox>
	</object>
	<object>
		<name>Lactacyd natural care 60ml</name>
		<pose>Unspecified</pose>
		<truncated>0</truncated>
		<difficult>0</difficult>
		<bndbox>
			<xmin>447</xmin>
			<ymin>1195</ymin>
			<xmax>655</xmax>
			<ymax>1445</ymax>
		</bndbox>
	</object>
	<object>
		<name>Mamipoko wipes Blue</name>
		<pose>Unspecified</pose>
		<truncated>0</truncated>
		<difficult>0</difficult>
		<bndbox>
			<xmin>97</xmin>
			<ymin>871</ymin>
			<xmax>408</xmax>
			<ymax>1345</ymax>
		</bndbox>
	</object>
	<object>
		<name>Quantum gelo plus 2 pieces</name>
		<pose>Unspecified</pose>
		<truncated>0</truncated>
		<difficult>0</difficult>
		<bndbox>
			<xmin>388</xmin>
			<ymin>968</ymin>
			<xmax>997</xmax>
			<ymax>1192</ymax>
		</bndbox>
	</object>
	<object>
		<name>Rosdee pork 30g</name>
		<pose>Unspecified</pose>
		<truncated>0</truncated>
		<difficult>0</difficult>
		<bndbox>
			<xmin>185</xmin>
			<ymin>1418</ymin>
			<xmax>441</xmax>
			<ymax>1751</ymax>
		</bndbox>
	</object>
</annotation>
