<annotation><filename>270.jpg</filename><path>/home/palm/PycharmProjects/seven/data1/1/270.jpg</path><size><width>1080</width><height>1920</height></size><object><name>Moccona Trio Espresso 90g</name><bndbox><xmin>298</xmin><ymin>310</ymin><xmax>741</xmax><ymax>835</ymax></bndbox></object><object><name>Moccona Trio Gold 100g</name><bndbox><xmin>422</xmin><ymin>751</ymin><xmax>1009</xmax><ymax>1377</ymax></bndbox></object><object><name>Khao shong 3 in 1 espresso 90g</name><bndbox><xmin>28</xmin><ymin>580</ymin><xmax>427</xmax><ymax>1111</ymax></bndbox></object></annotation>