<annotation><filename>315.jpg</filename><path>/home/palm/PycharmProjects/seven/data1/1/315.jpg</path><size><width>1080</width><height>1920</height></size><object><name>Milo nuggets 30g</name><bndbox><xmin>65</xmin><ymin>456</ymin><xmax>400</xmax><ymax>827</ymax></bndbox></object><object><name>Moccona Trio rich and smooth 90g</name><bndbox><xmin>410</xmin><ymin>909</ymin><xmax>980</xmax><ymax>1511</ymax></bndbox></object><object><name>Moccona Trio rich and smooth 90g</name><bndbox><xmin>101</xmin><ymin>764</ymin><xmax>594</xmax><ymax>1252</ymax></bndbox></object><object><name>Sponser original 250ml</name><bndbox><xmin>547</xmin><ymin>280</ymin><xmax>1001</xmax><ymax>862</ymax></bndbox></object></annotation>