<annotation><filename>364.jpg</filename><path>/home/palm/PycharmProjects/seven/data1/1/364.jpg</path><size><width>1080</width><height>1920</height></size><object><name>Milo nuggets 30g</name><bndbox><xmin>384</xmin><ymin>1016</ymin><xmax>882</xmax><ymax>1663</ymax></bndbox></object><object><name>Soffel Flora 80ml</name><bndbox><xmin>384</xmin><ymin>173</ymin><xmax>702</xmax><ymax>732</ymax></bndbox></object><object><name>Lypon-F 150ml</name><bndbox><xmin>668</xmin><ymin>411</ymin><xmax>1047</xmax><ymax>890</ymax></bndbox></object><object><name>Dentyne splash straw 15.2g</name><bndbox><xmin>186</xmin><ymin>683</ymin><xmax>428</xmax><ymax>1052</ymax></bndbox></object><object><name>Kellogg's corn flakes 25g</name><bndbox><xmin>45</xmin><ymin>1122</ymin><xmax>348</xmax><ymax>1562</ymax></bndbox></object></annotation>