<annotation><filename>617.jpg</filename><path>/home/palm/PycharmProjects/seven/data1/1/617.jpg</path><size><width>1080</width><height>1920</height></size><object><name>obj</name><bndbox><xmin>33</xmin><ymin>757</ymin><xmax>351</xmax><ymax>1212</ymax></bndbox></object><object><name>Mamipoko wipes Blue</name><bndbox><xmin>178</xmin><ymin>1342</ymin><xmax>538</xmax><ymax>1914</ymax></bndbox></object><object><name>obj</name><bndbox><xmin>381</xmin><ymin>728</ymin><xmax>925</xmax><ymax>1285</ymax></bndbox></object></annotation>