<annotation><filename>706.jpg</filename><path>/home/palm/PycharmProjects/seven/data1/1/706.jpg</path><size><width>1080</width><height>1920</height></size><object><name>Me-O tuna 450g</name><bndbox><xmin>234</xmin><ymin>417</ymin><xmax>564</xmax><ymax>843</ymax></bndbox></object><object><name>obj</name><bndbox><xmin>370</xmin><ymin>994</ymin><xmax>821</xmax><ymax>1489</ymax></bndbox></object><object><name>Benice 90ml</name><bndbox><xmin>21</xmin><ymin>829</ymin><xmax>287</xmax><ymax>1207</ymax></bndbox></object></annotation>