<annotation><filename>777.jpg</filename><path>/home/palm/PycharmProjects/seven/data1/1/777.jpg</path><size><width>1080</width><height>1920</height></size><object><name>Cosmetics</name><bndbox><xmin>367</xmin><ymin>1222</ymin><xmax>952</xmax><ymax>1764</ymax></bndbox></object><object><name>obj</name><bndbox><xmin>3</xmin><ymin>849</ymin><xmax>302</xmax><ymax>1274</ymax></bndbox></object><object><name>obj</name><bndbox><xmin>316</xmin><ymin>858</ymin><xmax>807</xmax><ymax>1234</ymax></bndbox></object><object><name>obj</name><bndbox><xmin>43</xmin><ymin>1392</ymin><xmax>363</xmax><ymax>1766</ymax></bndbox></object></annotation>