<annotation><filename>780.jpg</filename><path>/home/palm/PycharmProjects/seven/data1/1/780.jpg</path><size><width>1080</width><height>1920</height></size><object><name>Jabjab gummy jelly soda poppu 50g</name><bndbox><xmin>365</xmin><ymin>778</ymin><xmax>886</xmax><ymax>1181</ymax></bndbox></object><object><name>Jolly cola 25g</name><bndbox><xmin>5</xmin><ymin>784</ymin><xmax>341</xmax><ymax>1209</ymax></bndbox></object><object><name>Pipo gummy filled 70g</name><bndbox><xmin>391</xmin><ymin>1172</ymin><xmax>898</xmax><ymax>1661</ymax></bndbox></object><object><name>Haribo goldbear</name><bndbox><xmin>22</xmin><ymin>1321</ymin><xmax>346</xmax><ymax>1749</ymax></bndbox></object></annotation>