<annotation><filename>114.jpg</filename><path>/home/palm/PycharmProjects/seven/data1/1/114.jpg</path><size><width>1080</width><height>1920</height></size><object><name>obj</name><bndbox><xmin>264</xmin><ymin>783</ymin><xmax>666</xmax><ymax>1047</ymax></bndbox></object><object><name>obj</name><bndbox><xmin>388</xmin><ymin>268</ymin><xmax>749</xmax><ymax>601</ymax></bndbox></object><object><name>obj</name><bndbox><xmin>35</xmin><ymin>719</ymin><xmax>274</xmax><ymax>1041</ymax></bndbox></object><object><name>obj</name><bndbox><xmin>37</xmin><ymin>273</ymin><xmax>295</xmax><ymax>644</ymax></bndbox></object><object><name>obj</name><bndbox><xmin>11</xmin><ymin>1342</ymin><xmax>271</xmax><ymax>1901</ymax></bndbox></object></annotation>