<annotation><filename>164.jpg</filename><path>/home/palm/PycharmProjects/seven/data1/1/164.jpg</path><size><width>1080</width><height>1920</height></size><object><name>obj</name><bndbox><xmin>205</xmin><ymin>183</ymin><xmax>588</xmax><ymax>897</ymax></bndbox></object><object><name>obj</name><bndbox><xmin>108</xmin><ymin>1076</ymin><xmax>637</xmax><ymax>1866</ymax></bndbox></object><object><name>obj</name><bndbox><xmin>525</xmin><ymin>616</ymin><xmax>1054</xmax><ymax>1637</ymax></bndbox></object><object><name>obj</name><bndbox><xmin>2</xmin><ymin>726</ymin><xmax>240</xmax><ymax>1346</ymax></bndbox></object></annotation>