<annotation><filename>407.jpg</filename><path>/home/palm/PycharmProjects/seven/data1/1/407.jpg</path><size><width>1080</width><height>1920</height></size><object><name>obj</name><bndbox><xmin>318</xmin><ymin>1333</ymin><xmax>910</xmax><ymax>1709</ymax></bndbox></object><object><name>obj</name><bndbox><xmin>168</xmin><ymin>756</ymin><xmax>540</xmax><ymax>1253</ymax></bndbox></object><object><name>obj</name><bndbox><xmin>58</xmin><ymin>74</ymin><xmax>798</xmax><ymax>729</ymax></bndbox></object></annotation>