<annotation><filename>473.jpg</filename><path>/home/palm/PycharmProjects/seven/data1/1/473.jpg</path><size><width>1080</width><height>1920</height></size><object><name>obj</name><bndbox><xmin>160</xmin><ymin>1312</ymin><xmax>988</xmax><ymax>1920</ymax></bndbox></object><object><name>obj</name><bndbox><xmin>0</xmin><ymin>659</ymin><xmax>369</xmax><ymax>1268</ymax></bndbox></object><object><name>obj</name><bndbox><xmin>274</xmin><ymin>569</ymin><xmax>729</xmax><ymax>1356</ymax></bndbox></object><object><name>obj</name><bndbox><xmin>157</xmin><ymin>586</ymin><xmax>392</xmax><ymax>768</ymax></bndbox></object><object><name>obj</name><bndbox><xmin>292</xmin><ymin>279</ymin><xmax>731</xmax><ymax>1068</ymax></bndbox></object><object><name>obj</name><bndbox><xmin>142</xmin><ymin>88</ymin><xmax>803</xmax><ymax>882</ymax></bndbox></object></annotation>