<annotation><filename>584.jpg</filename><path>/home/palm/PycharmProjects/seven/data1/1/584.jpg</path><size><width>1080</width><height>1920</height></size><object><name>obj</name><bndbox><xmin>23</xmin><ymin>880</ymin><xmax>449</xmax><ymax>1618</ymax></bndbox></object><object><name>obj</name><bndbox><xmin>195</xmin><ymin>442</ymin><xmax>948</xmax><ymax>889</ymax></bndbox></object><object><name>obj</name><bndbox><xmin>144</xmin><ymin>1528</ymin><xmax>636</xmax><ymax>1920</ymax></bndbox></object></annotation>