<annotation><filename>59.jpg</filename><path>/home/palm/PycharmProjects/seven/data1/1/59.jpg</path><size><width>1080</width><height>1920</height></size><object><name>obj</name><bndbox><xmin>460</xmin><ymin>745</ymin><xmax>924</xmax><ymax>1079</ymax></bndbox></object><object><name>obj</name><bndbox><xmin>220</xmin><ymin>1119</ymin><xmax>630</xmax><ymax>1650</ymax></bndbox></object><object><name>obj</name><bndbox><xmin>275</xmin><ymin>654</ymin><xmax>487</xmax><ymax>1165</ymax></bndbox></object><object><name>obj</name><bndbox><xmin>47</xmin><ymin>878</ymin><xmax>266</xmax><ymax>1209</ymax></bndbox></object><object><name>obj</name><bndbox><xmin>212</xmin><ymin>532</ymin><xmax>438</xmax><ymax>1080</ymax></bndbox></object><object><name>obj</name><bndbox><xmin>129</xmin><ymin>473</ymin><xmax>382</xmax><ymax>903</ymax></bndbox></object><object><name>obj</name><bndbox><xmin>95</xmin><ymin>739</ymin><xmax>430</xmax><ymax>1191</ymax></bndbox></object></annotation>