<annotation><filename>658.jpg</filename><path>/home/palm/PycharmProjects/seven/data1/1/658.jpg</path><size><width>1080</width><height>1920</height></size><object><name>obj</name><bndbox><xmin>532</xmin><ymin>1069</ymin><xmax>1013</xmax><ymax>1697</ymax></bndbox></object><object><name>obj</name><bndbox><xmin>240</xmin><ymin>390</ymin><xmax>789</xmax><ymax>1031</ymax></bndbox></object><object><name>obj</name><bndbox><xmin>39</xmin><ymin>1005</ymin><xmax>389</xmax><ymax>1557</ymax></bndbox></object></annotation>