<annotation><filename>831.jpg</filename><path>/home/palm/PycharmProjects/seven/data1/1/831.jpg</path><size><width>1080</width><height>1920</height></size><object><name>obj</name><bndbox><xmin>323</xmin><ymin>1206</ymin><xmax>845</xmax><ymax>1657</ymax></bndbox></object><object><name>obj</name><bndbox><xmin>0</xmin><ymin>868</ymin><xmax>323</xmax><ymax>1328</ymax></bndbox></object><object><name>obj</name><bndbox><xmin>328</xmin><ymin>839</ymin><xmax>843</xmax><ymax>1200</ymax></bndbox></object><object><name>obj</name><bndbox><xmin>13</xmin><ymin>1311</ymin><xmax>332</xmax><ymax>1730</ymax></bndbox></object><object><name>obj</name><bndbox><xmin>547</xmin><ymin>0</ymin><xmax>977</xmax><ymax>512</ymax></bndbox></object><object><name>obj</name><bndbox><xmin>911</xmin><ymin>216</ymin><xmax>1080</xmax><ymax>537</ymax></bndbox></object><object><name>obj</name><bndbox><xmin>0</xmin><ymin>1059</ymin><xmax>326</xmax><ymax>1606</ymax></bndbox></object></annotation>