<annotation><filename>1769.jpg</filename><path>/home/palm/PycharmProjects/seven/data1/2/1769.jpg</path><size><width>1080</width><height>1920</height></size><object><name>Milo serials box 25g</name><bndbox><xmin>173</xmin><ymin>1428</ymin><xmax>638</xmax><ymax>1920</ymax></bndbox></object><object><name>Lotte xylitol lime mint 11.6g</name><bndbox><xmin>505</xmin><ymin>674</ymin><xmax>858</xmax><ymax>1248</ymax></bndbox></object><object><name>Abacus pink 30g</name><bndbox><xmin>167</xmin><ymin>854</ymin><xmax>409</xmax><ymax>1176</ymax></bndbox></object></annotation>