<annotation><filename>2118.jpg</filename><path>/home/palm/PycharmProjects/seven/data1/2/2118.jpg</path><size><width>1080</width><height>1920</height></size><object><name>Cream o choco plus cappucino 60g</name><bndbox><xmin>98</xmin><ymin>826</ymin><xmax>328</xmax><ymax>1221</ymax></bndbox></object><object><name>C-vit lemon 140 ml</name><bndbox><xmin>479</xmin><ymin>386</ymin><xmax>654</xmax><ymax>829</ymax></bndbox></object><object><name>Vaseline healthy white 75g</name><bndbox><xmin>551</xmin><ymin>880</ymin><xmax>820</xmax><ymax>1193</ymax></bndbox></object></annotation>