<annotation><filename>1624.jpg</filename><path>/home/palm/PycharmProjects/seven/data1/3/1624.jpg</path><size><width>1080</width><height>1920</height></size><object><name>obj</name><bndbox><xmin>83</xmin><ymin>1035</ymin><xmax>469</xmax><ymax>1452</ymax></bndbox></object><object><name>obj</name><bndbox><xmin>498</xmin><ymin>1105</ymin><xmax>1032</xmax><ymax>1485</ymax></bndbox></object><object><name>obj</name><bndbox><xmin>532</xmin><ymin>301</ymin><xmax>999</xmax><ymax>807</ymax></bndbox></object><object><name>obj</name><bndbox><xmin>123</xmin><ymin>460</ymin><xmax>420</xmax><ymax>943</ymax></bndbox></object></annotation>