<annotation><filename>1674.jpg</filename><path>/home/palm/PycharmProjects/seven/data1/3/1674.jpg</path><size><width>1080</width><height>1920</height></size><object><name>obj</name><bndbox><xmin>0</xmin><ymin>580</ymin><xmax>517</xmax><ymax>924</ymax></bndbox></object><object><name>obj</name><bndbox><xmin>25</xmin><ymin>912</ymin><xmax>365</xmax><ymax>1205</ymax></bndbox></object><object><name>obj</name><bndbox><xmin>457</xmin><ymin>846</ymin><xmax>973</xmax><ymax>1134</ymax></bndbox></object><object><name>obj</name><bndbox><xmin>561</xmin><ymin>1236</ymin><xmax>815</xmax><ymax>1416</ymax></bndbox></object><object><name>obj</name><bndbox><xmin>541</xmin><ymin>980</ymin><xmax>958</xmax><ymax>1234</ymax></bndbox></object></annotation>