<annotation><filename>1734.jpg</filename><path>/home/palm/PycharmProjects/seven/data1/3/1734.jpg</path><size><width>1080</width><height>1920</height></size><object><name>obj</name><bndbox><xmin>134</xmin><ymin>1062</ymin><xmax>743</xmax><ymax>1415</ymax></bndbox></object><object><name>obj</name><bndbox><xmin>319</xmin><ymin>916</ymin><xmax>770</xmax><ymax>1166</ymax></bndbox></object><object><name>obj</name><bndbox><xmin>0</xmin><ymin>604</ymin><xmax>702</xmax><ymax>1069</ymax></bndbox></object></annotation>