<annotation><filename>1921.jpg</filename><path>/home/palm/PycharmProjects/seven/data1/3/1921.jpg</path><size><width>1080</width><height>1920</height></size><object><name>obj</name><bndbox><xmin>394</xmin><ymin>201</ymin><xmax>871</xmax><ymax>663</ymax></bndbox></object><object><name>obj</name><bndbox><xmin>557</xmin><ymin>832</ymin><xmax>1041</xmax><ymax>1242</ymax></bndbox></object><object><name>obj</name><bndbox><xmin>221</xmin><ymin>711</ymin><xmax>508</xmax><ymax>954</ymax></bndbox></object></annotation>