<annotation><filename>1987.jpg</filename><path>/home/palm/PycharmProjects/seven/data1/3/1987.jpg</path><size><width>1080</width><height>1920</height></size><object><name>obj</name><bndbox><xmin>589</xmin><ymin>249</ymin><xmax>1009</xmax><ymax>836</ymax></bndbox></object><object><name>obj</name><bndbox><xmin>364</xmin><ymin>418</ymin><xmax>927</xmax><ymax>1252</ymax></bndbox></object><object><name>obj</name><bndbox><xmin>301</xmin><ymin>626</ymin><xmax>742</xmax><ymax>1371</ymax></bndbox></object></annotation>