<annotation><filename>2179.jpg</filename><path>/home/palm/PycharmProjects/seven/data1/3/2179.jpg</path><size><width>1080</width><height>1920</height></size><object><name>obj</name><bndbox><xmin>521</xmin><ymin>254</ymin><xmax>1030</xmax><ymax>967</ymax></bndbox></object><object><name>obj</name><bndbox><xmin>161</xmin><ymin>608</ymin><xmax>464</xmax><ymax>1315</ymax></bndbox></object><object><name>obj</name><bndbox><xmin>135</xmin><ymin>555</ymin><xmax>347</xmax><ymax>1116</ymax></bndbox></object><object><name>obj</name><bndbox><xmin>434</xmin><ymin>698</ymin><xmax>624</xmax><ymax>1258</ymax></bndbox></object></annotation>