<annotation><filename>2473.jpg</filename><path>/home/palm/PycharmProjects/seven/data1/3/2473.jpg</path><size><width>1080</width><height>1920</height></size><object><name>obj</name><bndbox><xmin>601</xmin><ymin>218</ymin><xmax>1032</xmax><ymax>645</ymax></bndbox></object><object><name>obj</name><bndbox><xmin>113</xmin><ymin>495</ymin><xmax>364</xmax><ymax>1081</ymax></bndbox></object><object><name>obj</name><bndbox><xmin>579</xmin><ymin>974</ymin><xmax>1080</xmax><ymax>1605</ymax></bndbox></object></annotation>