<annotation><filename>2485.jpg</filename><path>/home/palm/PycharmProjects/seven/data1/3/2485.jpg</path><size><width>1080</width><height>1920</height></size><object><name>obj</name><bndbox><xmin>389</xmin><ymin>2</ymin><xmax>1062</xmax><ymax>491</ymax></bndbox></object><object><name>obj</name><bndbox><xmin>430</xmin><ymin>1144</ymin><xmax>1080</xmax><ymax>1397</ymax></bndbox></object><object><name>obj</name><bndbox><xmin>326</xmin><ymin>529</ymin><xmax>604</xmax><ymax>851</ymax></bndbox></object></annotation>