<annotation><filename>2719.jpg</filename><path>/home/palm/PycharmProjects/seven/data1/3/2719.jpg</path><size><width>1080</width><height>1920</height></size><object><name>obj</name><bndbox><xmin>48</xmin><ymin>547</ymin><xmax>455</xmax><ymax>833</ymax></bndbox></object><object><name>obj</name><bndbox><xmin>239</xmin><ymin>1022</ymin><xmax>766</xmax><ymax>1468</ymax></bndbox></object><object><name>obj</name><bndbox><xmin>476</xmin><ymin>178</ymin><xmax>1036</xmax><ymax>796</ymax></bndbox></object></annotation>