<annotation>
	<folder>1</folder>
	<filename>1_662.jpg</filename>
	<path>/home/palm/PycharmProjects/seven/data1/1_E:\Work\PIM\DeepLearning\data1\1\662.jpg</path>
	<source>
		<database>Unknown</database>
	</source>
	<size>
		<width>1080</width>
		<height>1920</height>
		<depth>3</depth>
	</size>
	<segmented>0</segmented>
	<object>
		<name>Strepsil Orange (6 tablets)</name>
		<pose>Unspecified</pose>
		<truncated>0</truncated>
		<difficult>0</difficult>
		<bndbox>
			<xmin>263</xmin>
			<ymin>970</ymin>
			<xmax>503</xmax>
			<ymax>1305</ymax>
		</bndbox>
	</object>
	<object>
		<name>Strepsil Honey &amp; Lemon (6 tablets)</name>
		<pose>Unspecified</pose>
		<truncated>0</truncated>
		<difficult>0</difficult>
		<bndbox>
			<xmin>415</xmin>
			<ymin>1252</ymin>
			<xmax>648</xmax>
			<ymax>1703</ymax>
		</bndbox>
	</object>
	<object>
		<name>Strepsil Citrus Lemon (6 tablets)</name>
		<pose>Unspecified</pose>
		<truncated>0</truncated>
		<difficult>0</difficult>
		<bndbox>
			<xmin>199</xmin>
			<ymin>659</ymin>
			<xmax>455</xmax>
			<ymax>989</ymax>
		</bndbox>
	</object>
</annotation>