<annotation><filename>2_1843.jpg</filename><path>/home/palm/PycharmProjects/seven/data1/2_1843.jpg</path><size><width>1080</width><height>1920</height></size><object><name>Khao shong 3 in 1 super rich 100g</name><bndbox><xmin>511</xmin><ymin>1013</ymin><xmax>820</xmax><ymax>1452</ymax></bndbox></object><object><name>Milo serials box 25g</name><bndbox><xmin>159</xmin><ymin>1065</ymin><xmax>447</xmax><ymax>1364</ymax></bndbox></object><object><name>C-vit lemon 140 ml</name><bndbox><xmin>393</xmin><ymin>735</ymin><xmax>579</xmax><ymax>993</ymax></bndbox></object></annotation>