<annotation>
	<folder>3</folder>
	<filename>3_2334.jpg</filename>
	<path>/home/palm/PycharmProjects/seven/data1/3_2334.jpg</path>
	<source>
		<database>Unknown</database>
	</source>
	<size>
		<width>1080</width>
		<height>1920</height>
		<depth>3</depth>
	</size>
	<segmented>0</segmented>
	<object>
		<name>Darlie green</name>
		<pose>Unspecified</pose>
		<truncated>0</truncated>
		<difficult>0</difficult>
		<bndbox>
			<xmin>350</xmin>
			<ymin>843</ymin>
			<xmax>727</xmax>
			<ymax>1350</ymax>
		</bndbox>
	</object>
	<object>
		<name>Rosdee pork 30g</name>
		<pose>Unspecified</pose>
		<truncated>1</truncated>
		<difficult>0</difficult>
		<bndbox>
			<xmin>754</xmin>
			<ymin>908</ymin>
			<xmax>1080</xmax>
			<ymax>1251</ymax>
		</bndbox>
	</object>
	<object>
		<name>Pentel soft erasor</name>
		<pose>Unspecified</pose>
		<truncated>0</truncated>
		<difficult>0</difficult>
		<bndbox>
			<xmin>650</xmin>
			<ymin>1245</ymin>
			<xmax>1052</xmax>
			<ymax>1432</ymax>
		</bndbox>
	</object>
	<object>
		<name>Kids scissor school work</name>
		<pose>Unspecified</pose>
		<truncated>0</truncated>
		<difficult>0</difficult>
		<bndbox>
			<xmin>123</xmin>
			<ymin>1308</ymin>
			<xmax>583</xmax>
			<ymax>1513</ymax>
		</bndbox>
	</object>
</annotation>