<annotation>
	<folder>3</folder>
	<filename>2216.jpg</filename>
	<path>D:\Users\Administrator\Desktop\golf_13-03\3\2216.jpg</path>
	<source>
		<database>Unknown</database>
	</source>
	<size>
		<width>1080</width>
		<height>1920</height>
		<depth>3</depth>
	</size>
	<segmented>0</segmented>
	<object>
		<name>Uhu glues 8.2g</name>
		<pose>Unspecified</pose>
		<truncated>0</truncated>
		<difficult>0</difficult>
		<bndbox>
			<xmin>159</xmin>
			<ymin>437</ymin>
			<xmax>432</xmax>
			<ymax>901</ymax>
		</bndbox>
	</object>
	<object>
		<name>Pentel soft erasor</name>
		<pose>Unspecified</pose>
		<truncated>0</truncated>
		<difficult>0</difficult>
		<bndbox>
			<xmin>421</xmin>
			<ymin>451</ymin>
			<xmax>662</xmax>
			<ymax>844</ymax>
		</bndbox>
	</object>
	<object>
		<name>Staedtler eraser 2 pieces</name>
		<pose>Unspecified</pose>
		<truncated>0</truncated>
		<difficult>0</difficult>
		<bndbox>
			<xmin>304</xmin>
			<ymin>946</ymin>
			<xmax>625</xmax>
			<ymax>1110</ymax>
		</bndbox>
	</object>
</annotation>
