<annotation>
	<folder>3</folder>
	<filename>2282.jpg</filename>
	<path>D:\Users\Administrator\Desktop\golf_13-03\3\2282.jpg</path>
	<source>
		<database>Unknown</database>
	</source>
	<size>
		<width>1080</width>
		<height>1920</height>
		<depth>3</depth>
	</size>
	<segmented>0</segmented>
	<object>
		<name>Kids scissor school work</name>
		<pose>Unspecified</pose>
		<truncated>0</truncated>
		<difficult>0</difficult>
		<bndbox>
			<xmin>243</xmin>
			<ymin>540</ymin>
			<xmax>682</xmax>
			<ymax>770</ymax>
		</bndbox>
	</object>
	<object>
		<name>Latex glue 3.5oz</name>
		<pose>Unspecified</pose>
		<truncated>0</truncated>
		<difficult>0</difficult>
		<bndbox>
			<xmin>616</xmin>
			<ymin>864</ymin>
			<xmax>794</xmax>
			<ymax>1024</ymax>
		</bndbox>
	</object>
	<object>
		<name>Pentel soft erasor</name>
		<pose>Unspecified</pose>
		<truncated>0</truncated>
		<difficult>0</difficult>
		<bndbox>
			<xmin>213</xmin>
			<ymin>824</ymin>
			<xmax>522</xmax>
			<ymax>1046</ymax>
		</bndbox>
	</object>
	<object>
		<name>Staedtler eraser 2 pieces</name>
		<pose>Unspecified</pose>
		<truncated>0</truncated>
		<difficult>0</difficult>
		<bndbox>
			<xmin>367</xmin>
			<ymin>1034</ymin>
			<xmax>676</xmax>
			<ymax>1358</ymax>
		</bndbox>
	</object>
</annotation>
