<annotation>
	<folder>3</folder>
	<filename>2652.jpg</filename>
	<path>C:\project711\golf_13-03\3\2652.jpg</path>
	<source>
		<database>Unknown</database>
	</source>
	<size>
		<width>1080</width>
		<height>1920</height>
		<depth>3</depth>
	</size>
	<segmented>0</segmented>
	<object>
		<name>Tong Garden Salted Almonds 35g</name>
		<pose>Unspecified</pose>
		<truncated>0</truncated>
		<difficult>0</difficult>
		<bndbox>
			<xmin>8</xmin>
			<ymin>803</ymin>
			<xmax>693</xmax>
			<ymax>1248</ymax>
		</bndbox>
	</object>
	<object>
		<name>Koh-Kae Salted Peanuts 42g</name>
		<pose>Unspecified</pose>
		<truncated>0</truncated>
		<difficult>0</difficult>
		<bndbox>
			<xmin>189</xmin>
			<ymin>1299</ymin>
			<xmax>734</xmax>
			<ymax>1610</ymax>
		</bndbox>
	</object>
</annotation>
