<annotation><filename>378.jpg</filename><path>/home/palm/PycharmProjects/seven/data1/0/378.jpg</path><size><width>1080</width><height>1920</height></size><object><name>Milo nuggets 30g</name><bndbox><xmin>568</xmin><ymin>824</ymin><xmax>1080</xmax><ymax>1707</ymax></bndbox></object><object><name>Moccona Trio rich and smooth 90g</name><bndbox><xmin>655</xmin><ymin>24</ymin><xmax>1069</xmax><ymax>898</ymax></bndbox></object><object><name>Khao shong 3 in 1 super rich 100g</name><bndbox><xmin>242</xmin><ymin>276</ymin><xmax>603</xmax><ymax>1063</ymax></bndbox></object><object><name>Losan cocoa 28g</name><bndbox><xmin>443</xmin><ymin>0</ymin><xmax>762</xmax><ymax>296</ymax></bndbox></object></annotation>