<annotation><filename>678.jpg</filename><path>/home/palm/PycharmProjects/seven/data1/0/678.jpg</path><size><width>1080</width><height>1920</height></size><object><name>Milo choco bar 15g</name><bndbox><xmin>406</xmin><ymin>1157</ymin><xmax>928</xmax><ymax>1809</ymax></bndbox></object><object><name>Dentyne splash mint 15.2g</name><bndbox><xmin>488</xmin><ymin>358</ymin><xmax>881</xmax><ymax>1122</ymax></bndbox></object><object><name>Fun-o power 50g</name><bndbox><xmin>2</xmin><ymin>1066</ymin><xmax>370</xmax><ymax>1573</ymax></bndbox></object><object><name>Cream o choco plus cappucino 60g</name><bndbox><xmin>42</xmin><ymin>1685</ymin><xmax>469</xmax><ymax>1920</ymax></bndbox></object><object><name>Bissin 36g</name><bndbox><xmin>22</xmin><ymin>820</ymin><xmax>333</xmax><ymax>1179</ymax></bndbox></object><object><name>obj</name><bndbox><xmin>12</xmin><ymin>885</ymin><xmax>341</xmax><ymax>1393</ymax></bndbox></object></annotation>