<annotation><filename>732.jpg</filename><path>/home/palm/PycharmProjects/seven/data1/0/732.jpg</path><size><width>1080</width><height>1920</height></size><object><name>Hacks regular 18.9g</name><bndbox><xmin>390</xmin><ymin>1457</ymin><xmax>915</xmax><ymax>1917</ymax></bndbox></object><object><name>Lypon-F 150ml</name><bndbox><xmin>394</xmin><ymin>619</ymin><xmax>1036</xmax><ymax>1030</ymax></bndbox></object><object><name>Oreo original 29.4g</name><bndbox><xmin>280</xmin><ymin>1086</ymin><xmax>808</xmax><ymax>1482</ymax></bndbox></object><object><name>Corifine C 14.4g</name><bndbox><xmin>106</xmin><ymin>1187</ymin><xmax>399</xmax><ymax>1805</ymax></bndbox></object><object><name>Citronella mosquito repellant 75ml</name><bndbox><xmin>488</xmin><ymin>983</ymin><xmax>898</xmax><ymax>1243</ymax></bndbox></object><object><name>obj</name><bndbox><xmin>359</xmin><ymin>1288</ymin><xmax>869</xmax><ymax>1775</ymax></bndbox></object><object><name>obj</name><bndbox><xmin>155</xmin><ymin>1088</ymin><xmax>600</xmax><ymax>1619</ymax></bndbox></object></annotation>