<annotation><filename>1189.jpg</filename><path>/home/palm/PycharmProjects/seven/data1/2/1189.jpg</path><size><width>1080</width><height>1920</height></size><object><name>Milo serials box 25g</name><bndbox><xmin>153</xmin><ymin>984</ymin><xmax>482</xmax><ymax>1328</ymax></bndbox></object><object><name>obj</name><bndbox><xmin>452</xmin><ymin>1215</ymin><xmax>866</xmax><ymax>1683</ymax></bndbox></object><object><name>Kellogg's corn flakes 25g</name><bndbox><xmin>518</xmin><ymin>883</ymin><xmax>832</xmax><ymax>1189</ymax></bndbox></object></annotation>