<annotation><filename>1189.jpg</filename><path>/home/palm/PycharmProjects/seven/data1/2/1189.jpg</path><size><width>1080</width><height>1920</height></size><object><name>obj</name><bndbox><xmin>459</xmin><ymin>1198</ymin><xmax>845</xmax><ymax>1681</ymax></bndbox></object><object><name>Fun-o custard 45g</name><bndbox><xmin>164</xmin><ymin>985</ymin><xmax>467</xmax><ymax>1325</ymax></bndbox></object><object><name>Kellogg's corn flakes 25g</name><bndbox><xmin>514</xmin><ymin>886</ymin><xmax>815</xmax><ymax>1199</ymax></bndbox></object></annotation>