<annotation><filename>119.jpg</filename><path>/home/palm/PycharmProjects/seven/data1/2/119.jpg</path><size><width>1080</width><height>1920</height></size><object><name>Moccona Trio Espresso 90g</name><bndbox><xmin>454</xmin><ymin>522</ymin><xmax>1067</xmax><ymax>1153</ymax></bndbox></object><object><name>obj</name><bndbox><xmin>523</xmin><ymin>1313</ymin><xmax>1065</xmax><ymax>1831</ymax></bndbox></object><object><name>Kitkat green tea 35g</name><bndbox><xmin>601</xmin><ymin>0</ymin><xmax>1058</xmax><ymax>379</ymax></bndbox></object></annotation>