<annotation><filename>1278.jpg</filename><path>/home/palm/PycharmProjects/seven/data1/2/1278.jpg</path><size><width>1080</width><height>1920</height></size><object><name>obj</name><bndbox><xmin>598</xmin><ymin>692</ymin><xmax>1018</xmax><ymax>949</ymax></bndbox></object><object><name>Almond_Fried_56G</name><bndbox><xmin>24</xmin><ymin>958</ymin><xmax>749</xmax><ymax>1417</ymax></bndbox></object><object><name>Milo serials box 25g</name><bndbox><xmin>134</xmin><ymin>636</ymin><xmax>545</xmax><ymax>929</ymax></bndbox></object></annotation>