<annotation><filename>1304.jpg</filename><path>/home/palm/PycharmProjects/seven/data1/2/1304.jpg</path><size><width>1080</width><height>1920</height></size><object><name>obj</name><bndbox><xmin>272</xmin><ymin>466</ymin><xmax>857</xmax><ymax>675</ymax></bndbox></object><object><name>Moccona Trio Espresso 90g</name><bndbox><xmin>162</xmin><ymin>867</ymin><xmax>497</xmax><ymax>1533</ymax></bndbox></object><object><name>obj</name><bndbox><xmin>480</xmin><ymin>815</ymin><xmax>1064</xmax><ymax>1798</ymax></bndbox></object></annotation>