<annotation><filename>1305.jpg</filename><path>/home/palm/PycharmProjects/seven/data1/2/1305.jpg</path><size><width>1080</width><height>1920</height></size><object><name>obj</name><bndbox><xmin>117</xmin><ymin>706</ymin><xmax>713</xmax><ymax>1086</ymax></bndbox></object><object><name>Moccona Trio Espresso 90g</name><bndbox><xmin>693</xmin><ymin>788</ymin><xmax>1080</xmax><ymax>1148</ymax></bndbox></object><object><name>Citronella mosquito repellant 75ml</name><bndbox><xmin>253</xmin><ymin>1128</ymin><xmax>799</xmax><ymax>1400</ymax></bndbox></object></annotation>