<annotation><filename>1310.jpg</filename><path>/home/palm/PycharmProjects/seven/data1/2/1310.jpg</path><size><width>1080</width><height>1920</height></size><object><name>obj</name><bndbox><xmin>176</xmin><ymin>825</ymin><xmax>484</xmax><ymax>1540</ymax></bndbox></object><object><name>7 select cooly fresh 350ml</name><bndbox><xmin>530</xmin><ymin>754</ymin><xmax>1074</xmax><ymax>1750</ymax></bndbox></object><object><name>Citronella mosquito repellant 75ml</name><bndbox><xmin>313</xmin><ymin>457</ymin><xmax>801</xmax><ymax>675</ymax></bndbox></object></annotation>