<annotation><filename>1368.jpg</filename><path>/home/palm/PycharmProjects/seven/data1/2/1368.jpg</path><size><width>1080</width><height>1920</height></size><object><name>Halls honey 22.4g</name><bndbox><xmin>647</xmin><ymin>856</ymin><xmax>1039</xmax><ymax>1215</ymax></bndbox></object><object><name>obj</name><bndbox><xmin>639</xmin><ymin>441</ymin><xmax>919</xmax><ymax>818</ymax></bndbox></object><object><name>obj</name><bndbox><xmin>155</xmin><ymin>841</ymin><xmax>640</xmax><ymax>1188</ymax></bndbox></object></annotation>