<annotation><filename>1393.jpg</filename><path>/home/palm/PycharmProjects/seven/data1/2/1393.jpg</path><size><width>1080</width><height>1920</height></size><object><name>Ole super sour 17.5g</name><bndbox><xmin>357</xmin><ymin>1072</ymin><xmax>742</xmax><ymax>1332</ymax></bndbox></object><object><name>Dentyne ice 11.2g</name><bndbox><xmin>367</xmin><ymin>1362</ymin><xmax>648</xmax><ymax>1593</ymax></bndbox></object><object><name>Baby mild ultra mild 125ml</name><bndbox><xmin>429</xmin><ymin>755</ymin><xmax>609</xmax><ymax>1002</ymax></bndbox></object></annotation>