<annotation><filename>1546.jpg</filename><path>/home/palm/PycharmProjects/seven/data1/2/1546.jpg</path><size><width>1080</width><height>1920</height></size><object><name>Jolly cola 25g</name><bndbox><xmin>200</xmin><ymin>1170</ymin><xmax>476</xmax><ymax>1448</ymax></bndbox></object><object><name>Take-it Black</name><bndbox><xmin>553</xmin><ymin>1109</ymin><xmax>821</xmax><ymax>1415</ymax></bndbox></object><object><name>Toppo cocoa pretzel stick 11g</name><bndbox><xmin>305</xmin><ymin>702</ymin><xmax>525</xmax><ymax>1033</ymax></bndbox></object></annotation>