<annotation><filename>1659.jpg</filename><path>/home/palm/PycharmProjects/seven/data1/2/1659.jpg</path><size><width>1080</width><height>1920</height></size><object><name>Cosmetics</name><bndbox><xmin>430</xmin><ymin>450</ymin><xmax>627</xmax><ymax>842</ymax></bndbox></object><object><name>Fun-o chocolate cream 45g</name><bndbox><xmin>141</xmin><ymin>857</ymin><xmax>467</xmax><ymax>1290</ymax></bndbox></object><object><name>obj</name><bndbox><xmin>645</xmin><ymin>627</ymin><xmax>914</xmax><ymax>1141</ymax></bndbox></object></annotation>