<annotation><filename>1829.jpg</filename><path>/home/palm/PycharmProjects/seven/data1/2/1829.jpg</path><size><width>1080</width><height>1920</height></size><object><name>C-vit lemon 140 ml</name><bndbox><xmin>16</xmin><ymin>1580</ymin><xmax>506</xmax><ymax>1909</ymax></bndbox></object><object><name>Khao shong 3 in 1 super rich 100g</name><bndbox><xmin>143</xmin><ymin>698</ymin><xmax>478</xmax><ymax>1331</ymax></bndbox></object><object><name>Dentiste plus white 50g</name><bndbox><xmin>479</xmin><ymin>801</ymin><xmax>1069</xmax><ymax>1490</ymax></bndbox></object></annotation>