<annotation><filename>1842.jpg</filename><path>/home/palm/PycharmProjects/seven/data1/2/1842.jpg</path><size><width>1080</width><height>1920</height></size><object><name>Sponser original 250ml</name><bndbox><xmin>570</xmin><ymin>449</ymin><xmax>739</xmax><ymax>822</ymax></bndbox></object><object><name>7 select cooly fresh 350ml</name><bndbox><xmin>5</xmin><ymin>777</ymin><xmax>490</xmax><ymax>1136</ymax></bndbox></object><object><name>obj</name><bndbox><xmin>468</xmin><ymin>829</ymin><xmax>1042</xmax><ymax>1389</ymax></bndbox></object></annotation>