<annotation><filename>19.jpg</filename><path>/home/palm/PycharmProjects/seven/data1/2/19.jpg</path><size><width>1080</width><height>1920</height></size><object><name>obj</name><bndbox><xmin>295</xmin><ymin>777</ymin><xmax>577</xmax><ymax>1043</ymax></bndbox></object><object><name>Toppo cocoa pretzel stick 11g</name><bndbox><xmin>252</xmin><ymin>1230</ymin><xmax>571</xmax><ymax>1572</ymax></bndbox></object><object><name>obj</name><bndbox><xmin>523</xmin><ymin>1109</ymin><xmax>889</xmax><ymax>1338</ymax></bndbox></object></annotation>