<annotation><filename>1910.jpg</filename><path>/home/palm/PycharmProjects/seven/data1/2/1910.jpg</path><size><width>1080</width><height>1920</height></size><object><name>obj</name><bndbox><xmin>169</xmin><ymin>799</ymin><xmax>440</xmax><ymax>1211</ymax></bndbox></object><object><name>Me-O Tuna in jelly can 80g</name><bndbox><xmin>482</xmin><ymin>878</ymin><xmax>849</xmax><ymax>1238</ymax></bndbox></object><object><name>Bennett Orange soap (6 Pack)</name><bndbox><xmin>257</xmin><ymin>1579</ymin><xmax>715</xmax><ymax>1899</ymax></bndbox></object></annotation>