<annotation><filename>1931.jpg</filename><path>/home/palm/PycharmProjects/seven/data1/2/1931.jpg</path><size><width>1080</width><height>1920</height></size><object><name>Dettol original 65g</name><bndbox><xmin>549</xmin><ymin>831</ymin><xmax>904</xmax><ymax>1325</ymax></bndbox></object><object><name>Dentyne splash straw 15.2g</name><bndbox><xmin>235</xmin><ymin>905</ymin><xmax>467</xmax><ymax>1305</ymax></bndbox></object><object><name>Soffel fresh 80ml</name><bndbox><xmin>24</xmin><ymin>1592</ymin><xmax>424</xmax><ymax>1881</ymax></bndbox></object><object><name>Dentyne splash mint 15.2g</name><bndbox><xmin>514</xmin><ymin>1630</ymin><xmax>937</xmax><ymax>1920</ymax></bndbox></object></annotation>