<annotation><filename>1983.jpg</filename><path>/home/palm/PycharmProjects/seven/data1/2/1983.jpg</path><size><width>1080</width><height>1920</height></size><object><name>obj</name><bndbox><xmin>37</xmin><ymin>861</ymin><xmax>491</xmax><ymax>1180</ymax></bndbox></object><object><name>obj</name><bndbox><xmin>593</xmin><ymin>651</ymin><xmax>785</xmax><ymax>874</ymax></bndbox></object><object><name>obj</name><bndbox><xmin>477</xmin><ymin>876</ymin><xmax>876</xmax><ymax>1244</ymax></bndbox></object><object><name>Mamipoko wipes Blue</name><bndbox><xmin>269</xmin><ymin>445</ymin><xmax>464</xmax><ymax>799</ymax></bndbox></object></annotation>