<annotation><filename>2082.jpg</filename><path>/home/palm/PycharmProjects/seven/data1/2/2082.jpg</path><size><width>1080</width><height>1920</height></size><object><name>obj</name><bndbox><xmin>234</xmin><ymin>652</ymin><xmax>560</xmax><ymax>846</ymax></bndbox></object><object><name>obj</name><bndbox><xmin>45</xmin><ymin>862</ymin><xmax>413</xmax><ymax>1103</ymax></bndbox></object><object><name>obj</name><bndbox><xmin>519</xmin><ymin>830</ymin><xmax>882</xmax><ymax>1057</ymax></bndbox></object><object><name>Soffel fresh 80ml</name><bndbox><xmin>640</xmin><ymin>369</ymin><xmax>816</xmax><ymax>810</ymax></bndbox></object></annotation>