<annotation><filename>2131.jpg</filename><path>/home/palm/PycharmProjects/seven/data1/2/2131.jpg</path><size><width>1080</width><height>1920</height></size><object><name>Shokubutsu chinese milk 100ml</name><bndbox><xmin>496</xmin><ymin>871</ymin><xmax>736</xmax><ymax>1136</ymax></bndbox></object><object><name>obj</name><bndbox><xmin>542</xmin><ymin>1178</ymin><xmax>801</xmax><ymax>1434</ymax></bndbox></object><object><name>obj</name><bndbox><xmin>224</xmin><ymin>1250</ymin><xmax>481</xmax><ymax>1440</ymax></bndbox></object><object><name>Bennett Orange soap (6 Pack)</name><bndbox><xmin>240</xmin><ymin>867</ymin><xmax>401</xmax><ymax>1172</ymax></bndbox></object></annotation>