<annotation><filename>243.jpg</filename><path>/home/palm/PycharmProjects/seven/data1/2/243.jpg</path><size><width>1080</width><height>1920</height></size><object><name>Haribo goldbear</name><bndbox><xmin>532</xmin><ymin>710</ymin><xmax>953</xmax><ymax>892</ymax></bndbox></object><object><name>Break SUPA 30g</name><bndbox><xmin>160</xmin><ymin>1344</ymin><xmax>1039</xmax><ymax>1658</ymax></bndbox></object><object><name>Hand!!!!</name><bndbox><xmin>51</xmin><ymin>965</ymin><xmax>350</xmax><ymax>1179</ymax></bndbox></object><object><name>Take-it Black</name><bndbox><xmin>573</xmin><ymin>946</ymin><xmax>974</xmax><ymax>1169</ymax></bndbox></object></annotation>