<annotation><filename>324.jpg</filename><path>/home/palm/PycharmProjects/seven/data1/2/324.jpg</path><size><width>1080</width><height>1920</height></size><object><name>M&amp;M peanut 40g</name><bndbox><xmin>36</xmin><ymin>812</ymin><xmax>536</xmax><ymax>1171</ymax></bndbox></object><object><name>obj</name><bndbox><xmin>540</xmin><ymin>623</ymin><xmax>856</xmax><ymax>871</ymax></bndbox></object><object><name>Almond_Fried_56G</name><bndbox><xmin>532</xmin><ymin>906</ymin><xmax>1080</xmax><ymax>1589</ymax></bndbox></object></annotation>