<annotation><filename>352.jpg</filename><path>/home/palm/PycharmProjects/seven/data1/2/352.jpg</path><size><width>1080</width><height>1920</height></size><object><name>Kitkat green tea 35g</name><bndbox><xmin>440</xmin><ymin>884</ymin><xmax>698</xmax><ymax>1108</ymax></bndbox></object><object><name>Ferrero 37.5g</name><bndbox><xmin>563</xmin><ymin>1117</ymin><xmax>855</xmax><ymax>1357</ymax></bndbox></object><object><name>obj</name><bndbox><xmin>315</xmin><ymin>1108</ymin><xmax>464</xmax><ymax>1450</ymax></bndbox></object></annotation>